jsscraper/__init__.py
jsscraper-0.0.1.dist-info/LICENSES.txt
jsscraper-0.0.1.dist-info/METADATA
jsscraper-0.0.1.dist-info/WHEEL
jsscraper-0.0.1.dist-info/top_level.txt
jsscraper-0.0.1.dist-info/RECORD
