Metadata-Version: 2.1
Name: jsscraper
Version: 0.0.1
Summary: This package can scrape data from java script
Author: Tufaah
Author-email: yazanemails@gmail.com
Keywords: scraper,js scraper,scrape,java script scraper
Classifier: Development Status :: 1 - Planning
Classifier: Intended Audience :: Developers
Classifier: Programming Language :: Python :: 3
Classifier: Operating System :: Unix
Classifier: Operating System :: MacOS :: MacOS X
Classifier: Operating System :: Microsoft :: Windows
License-File: LICENSES.txt
